{"app":{"id":"application_1592095354219_0021","user":"root","name":"grep-search","queue":"default","state":"FINISHED","finalStatus":"SUCCEEDED","progress":100.0,"trackingUI":"History","trackingUrl":"http://master:8088/proxy/application_1592095354219_0021/","diagnostics":"","clusterId":1592095354219,"applicationType":"MAPREDUCE","applicationTags":"","startedTime":1592100109368,"finishedTime":1592100533520,"elapsedTime":424152,"amContainerLogs":"http://elec-com-eng-p27.unist.ac.kr:8042/node/containerlogs/container_1592095354219_0021_01_000001/root","amHostHttpAddress":"elec-com-eng-p27.unist.ac.kr:8042","allocatedMB":-1,"allocatedVCores":-1,"runningContainers":-1,"memorySeconds":4878541,"vcoreSeconds":4286,"preemptedResourceMB":0,"preemptedResourceVCores":0,"numNonAMContainerPreempted":0,"numAMContainerPreempted":0}}